ebb_time_series/__init__.py
ebb_time_series/constants.py
ebb_time_series/event_parser_helpers.py
ebb_time_series/exceptions.py
ebb_time_series/writers/aws_timestream_data_writer.py
ebb_time_series/writers/base_data_writer.py
ebb_time_series-2.0.0.dist-info/LICENSE
ebb_time_series-2.0.0.dist-info/METADATA
ebb_time_series-2.0.0.dist-info/WHEEL
ebb_time_series-2.0.0.dist-info/RECORD
