Metadata-Version: 2.1
Name: ebb-time-series
Version: 2.0.0
Summary: 
Author: Ryan Bloom
Author-email: ryan.bloom@ebbcarbon.com
Requires-Python: >=3.10,<4.0
Classifier: Programming Language :: Python :: 3
Classifier: Programming Language :: Python :: 3.10
Classifier: Programming Language :: Python :: 3.11
Classifier: Programming Language :: Python :: 3.12
Requires-Dist: boto3 (>=1.34.103,<2.0.0)
Requires-Dist: botocore (>=1.34.103,<2.0.0)
Requires-Dist: ebb-events (>=1.0.0,<2.0.0)
